LICENSE
MANIFEST.in
README.md
setup.cfg
setup.py
tap_ordway/__init__.py
tap_ordway/__version__.py
tap_ordway/base.py
tap_ordway/configs.py
tap_ordway/kafka_consumer.py
tap_ordway/property.py
tap_ordway/utils.py
tap_ordway.egg-info/PKG-INFO
tap_ordway.egg-info/SOURCES.txt
tap_ordway.egg-info/dependency_links.txt
tap_ordway.egg-info/entry_points.txt
tap_ordway.egg-info/requires.txt
tap_ordway.egg-info/top_level.txt
tap_ordway/api/__init__.py
tap_ordway/api/base.py
tap_ordway/api/consts.py
tap_ordway/api/utils.py
tap_ordway/schemas/billing_runs.json
tap_ordway/schemas/billing_schedules.json
tap_ordway/schemas/charges.json
tap_ordway/schemas/chart_of_accounts.json
tap_ordway/schemas/contacts.json
tap_ordway/schemas/coupons.json
tap_ordway/schemas/credits.json
tap_ordway/schemas/customer_notes.json
tap_ordway/schemas/customers.json
tap_ordway/schemas/debit_memo.json
tap_ordway/schemas/invoices.json
tap_ordway/schemas/journal_entries.json
tap_ordway/schemas/orders.json
tap_ordway/schemas/payment_methods.json
tap_ordway/schemas/payment_runs.json
tap_ordway/schemas/payments.json
tap_ordway/schemas/plans.json
tap_ordway/schemas/products.json
tap_ordway/schemas/refunds.json
tap_ordway/schemas/revenue_rules.json
tap_ordway/schemas/revenue_schedules.json
tap_ordway/schemas/statements.json
tap_ordway/schemas/subscriptions.json
tap_ordway/schemas/usages.json
tap_ordway/schemas/webhooks.json
tap_ordway/streams/__init__.py
tap_ordway/streams/base.py
tap_ordway/streams/definitions.py
tap_ordway/streams/exceptions.py
tap_ordway/streams/utils.py
tap_ordway/transformers/__init__.py
tap_ordway/transformers/base.py
tap_ordway/transformers/transformers.py