Metadata-Version: 2.4
Name: tap-ordway
Version: 0.4.5
Summary: Singer.io tap for extracting data
Home-page: http://singer.io
Author: Stitch
Keywords: singer ordway tap
Classifier: Programming Language :: Python :: 3 :: Only
Classifier: License :: OSI Approved :: GNU Affero General Public License v3
Classifier: Operating System :: OS Independent
License-File: LICENSE
Requires-Dist: singer-python==6.1.1
Requires-Dist: requests==2.32.5
Requires-Dist: kafka-python==2.2.15
Requires-Dist: inflection==0.5.1
Provides-Extra: dev
Requires-Dist: black==20.8b1; extra == "dev"
Requires-Dist: pylint==3.3.4; extra == "dev"
Requires-Dist: tox==3.20.1; extra == "dev"
Provides-Extra: testing
Requires-Dist: mypy; extra == "testing"
Requires-Dist: pytest==6.1.1; extra == "testing"
Requires-Dist: pytest-cov==2.10.1; extra == "testing"
Requires-Dist: pytest-xdist==2.1.0; extra == "testing"
Requires-Dist: vcrpy; extra == "testing"
Dynamic: author
Dynamic: classifier
Dynamic: description
Dynamic: description-content-type
Dynamic: home-page
Dynamic: keywords
Dynamic: license-file
Dynamic: provides-extra
Dynamic: requires-dist
Dynamic: summary
